scommit/__init__.py
scommit/scommit.py
semantic_commit-1.3.0.dist-info/LICENSE
semantic_commit-1.3.0.dist-info/METADATA
semantic_commit-1.3.0.dist-info/WHEEL
semantic_commit-1.3.0.dist-info/entry_points.txt
semantic_commit-1.3.0.dist-info/top_level.txt
semantic_commit-1.3.0.dist-info/RECORD
