Metadata-Version: 2.1
Name: semantic-commit
Version: 1.3.0
Summary: scommit: ChatGPT-generated commit messages
Home-page: https://github.com/Globe-Knowledge-Solutions/semantic-commit
Author: Ivan Yevenko, Brian Machado, Parth Sareen
Author-email: ivan@globe.engineer, psareen@uwaterloo.ca
License: MIT
License-File: LICENSE
Requires-Dist: openai
Requires-Dist: tiktoken
Requires-Dist: requests
Requires-Dist: transformers
